EXP_NO_30/sipo_4bit.v
module sipo_4bit(
input clk,
input rst,
input serial_in,
output [3:0] q
);

reg [3:0] shift_reg;

always @(posedge clk)
begin

if(rst)
    shift_reg <= 4'b0000;

else
    shift_reg <= {shift_reg[2:0],serial_in};

end

assign q = shift_reg;

endmodule

EXP_NO_30/tb_sipo_4bit.v
module tb_sipo_4bit;

reg clk;
reg rst;
reg serial_in;

wire [3:0] q;

sipo_4bit dut(
.clk(clk),
.rst(rst),
.serial_in(serial_in),
.q(q)
);

always #10 clk = ~clk;

initial begin

$dumpfile("sipo.vcd");
$dumpvars(0,tb_sipo_4bit);

clk = 0;
rst = 1;
serial_in = 0;

#20;
rst = 0;

// Shift in 1011

serial_in = 1; #20;
serial_in = 0; #20;
serial_in = 1; #20;
serial_in = 1; #20;

// Extra clocks

serial_in = 0; #40;

$finish;

end

initial begin

$monitor(
"time=%0t serial_in=%b q=%b",
$time,
serial_in,
q
);

end

endmodule

EXP_NO_30/sipo.vcd
$date
	Wed Jun  3 19:14:01 2026
$end
$version
	Icarus Verilog
$end
$timescale
	1s
$end
$scope module tb_sipo_4bit $end
$var wire 4 ! q [3:0] $end
$var reg 1 " clk $end
$var reg 1 # rst $end
$var reg 1 $ serial_in $end
$scope module dut $end
$var wire 1 " clk $end
$var wire 4 % q [3:0] $end
$var wire 1 # rst $end
$var wire 1 $ serial_in $end
$var reg 4 & shift_reg [3:0] $end
$upscope $end
$upscope $end
$enddefinitions $end
#0
$dumpvars
bx &
bx %
0$
1#
0"
bx !
$end
#10
b0 !
b0 %
b0 &
1"
#20
0"
1$
0#
#30
b1 !
b1 %
b1 &
1"
#40
0"
0$
#50
b10 !
b10 %
b10 &
1"
#60
0"
1$
#70
b101 !
b101 %
b101 &
1"
#80
0"
#90
b1011 !
b1011 %
b1011 &
1"
#100
0"
0$
#110
b110 !
b110 %
b110 &
1"
#120
0"
#130
b1100 !
b1100 %
b1100 &
1"
