EXP_NO_7/mux1_dataflow.v
module mux1_dataflow (
input a,b,c,
output f
);

assign f = (~a & b) | (a & b);

endmodule

EXP_NO_7/tb_mux1_dataflow.v
module tb_mux1_dataflow;

reg a,b,c;
wire f;

mux1_dataflow dut(
.a(a),
.b(b),
.c(c),
.f(f)
);

initial begin
$dumpfile("mux1_dataflow.vcd");
$dumpvars(0,tb_mux1_dataflow);

a=0;b=0;c=0; #10;
a=0;b=0;c=1; #10;
a=0;b=1;c=0; #10;
a=0;b=1;c=1; #10;
a=1;b=0;c=0; #10;
a=1;b=0;c=1; #10;
a=1;b=1;c=0; #10;
a=1;b=1;c=1; #10;

$finish;
end

initial
$monitor("time=%0t a=%b b=%b c=%b f=%b",
          $time,a,b,c,f);

endmodule

EXP_NO_7/mux1_dataflow.vcd
$date
	Sun May 31 18:33:27 2026
$end
$version
	Icarus Verilog
$end
$timescale
	1s
$end
$scope module tb_mux1_dataflow $end
$var wire 1 ! f $end
$var reg 1 " a $end
$var reg 1 # b $end
$var reg 1 $ c $end
$scope module dut $end
$var wire 1 " a $end
$var wire 1 # b $end
$var wire 1 $ c $end
$var wire 1 ! f $end
$upscope $end
$upscope $end
$enddefinitions $end
#0
$dumpvars
0$
0#
0"
0!
$end
#10
1$
#20
1!
0$
1#
#30
1$
#40
0!
0$
0#
1"
#50
1$
#60
1!
0$
1#
#70
1$
