EXP_NO_7/mux1.v
module mux1 (
input a , b , c ,
output reg f 	);

always @(*)begin 
case ({a,b})
  2'b00 : f = 0 ;
    2'b01 : f = 1 ;
      2'b10 : f = 0 ;
        2'b11 : f = 1 ;
  
endcase 
end endmodule

EXP_NO_7/tb_mux1.v
module tb_mux1;
reg a , b , c ;
wire f ;


mux1 m1 (
.a(a),.b(b),.c(c),.f(f));

initial begin 
$dumpfile("mux1.vcd");
$dumpvars(0,tb_mux1);
a = 0 ; b = 0 ; c = 0 ;
#10;
a = 0 ; b = 0 ; c = 1 ;
#10;
a = 0 ; b = 1 ; c = 0 ;
#10;
a = 0 ; b = 1 ; c = 1 ;
#10;
a = 1 ; b = 0 ; c = 0 ;
#10;
a = 1 ; b = 0 ; c = 1 ;
#10;
a = 1 ; b = 1 ; c = 0 ;
#10;
a = 1 ; b = 1 ; c = 1 ;
#10;
end 
initial begin 
$monitor ("time = %t , a = %b , b = %b , c= %b , out = %b",$time , a , b , c , f ); 
end 
endmodule

EXP_NO_7/mux1.vcd
$date
	Sun May 31 18:22:21 2026
$end
$version
	Icarus Verilog
$end
$timescale
	1s
$end
$scope module tb_mux1 $end
$var wire 1 ! f $end
$var reg 1 " a $end
$var reg 1 # b $end
$var reg 1 $ c $end
$scope module m1 $end
$var wire 1 " a $end
$var wire 1 # b $end
$var wire 1 $ c $end
$var reg 1 ! f $end
$upscope $end
$upscope $end
$enddefinitions $end
#0
$dumpvars
0$
0#
0"
0!
$end
#10
1$
#20
1!
0$
1#
#30
1$
#40
0!
0$
0#
1"
#50
1$
#60
1!
0$
1#
#70
1$
