EXP_NO_7/mux1_structural_gates.v
module mux1_structural_gates(
input a,b,c,
output f
);

wire na;
wire w1,w2;

not g1(na,a);

and g2(w1,na,b);
and g3(w2,a,b);

or g4(f,w1,w2);

endmodule

EXP_NO_7/tb_mux1_structural_gates.v
module tb_mux1_structural_gates;

reg a,b,c;
wire f;

mux1_structural_gates dut(
.a(a),
.b(b),
.c(c),
.f(f)
);

initial begin
$dumpfile("mux1_structural_gates.vcd");
$dumpvars(0,tb_mux1_structural_gates);

a=0;b=0;c=0; #10;
a=0;b=0;c=1; #10;
a=0;b=1;c=0; #10;
a=0;b=1;c=1; #10;
a=1;b=0;c=0; #10;
a=1;b=0;c=1; #10;
a=1;b=1;c=0; #10;
a=1;b=1;c=1; #10;

$finish;
end

initial
$monitor("time=%0t a=%b b=%b c=%b f=%b",
          $time,a,b,c,f);

endmodule

EXP_NO_7/mux1_structural_gates.vcd
$date
	Sun May 31 18:36:25 2026
$end
$version
	Icarus Verilog
$end
$timescale
	1s
$end
$scope module tb_mux1_structural_gates $end
$var wire 1 ! f $end
$var reg 1 " a $end
$var reg 1 # b $end
$var reg 1 $ c $end
$scope module dut $end
$var wire 1 " a $end
$var wire 1 # b $end
$var wire 1 $ c $end
$var wire 1 ! f $end
$var wire 1 % na $end
$var wire 1 & w1 $end
$var wire 1 ' w2 $end
$upscope $end
$upscope $end
$enddefinitions $end
#0
$dumpvars
0'
0&
1%
0$
0#
0"
0!
$end
#10
1$
#20
1!
1&
0$
1#
#30
1$
#40
0!
0&
0%
0$
0#
1"
#50
1$
#60
1!
1'
0$
1#
#70
1$
