EXP_NO_6/dec_4x16.v
module dec_4x16(
    input wire [3:0] a,
    output reg [15:0] b
);

    always @(*) begin 
        case (a) 
            4'd0  : b = 16'h0001;
            4'd1  : b = 16'h0002;
            4'd2  : b = 16'h0004;
            4'd3  : b = 16'h0008;
            4'd4  : b = 16'h0010;
            4'd5  : b = 16'h0020;
            4'd6  : b = 16'h0040;
            4'd7  : b = 16'h0080;
            4'd8  : b = 16'h0100;
            4'd9  : b = 16'h0200;
            4'd10 : b = 16'h0400;
            4'd11 : b = 16'h0800;
            4'd12 : b = 16'h1000;
            4'd13 : b = 16'h2000;
            4'd14 : b = 16'h4000;
            4'd15 : b = 16'h8000;
            default: b = 16'h0000;
        endcase 
    end

endmodule

EXP_NO_6/tb_dec_4x16.v
`timescale 1ns / 1ps

module tb_dec_4x16;
    reg [3:0] a;
    wire [15:0] b;

    dec_4x16 uut (
        .a(a),
        .b(b)
    );

    integer i;
    initial begin 
        $dumpfile("dec_4x16.vcd");
        $dumpvars(0, tb_dec_4x16);
        
        $monitor("Time=%0t | Input a=%d (%b) | Output b=%b", $time, a, a, b);
        
        for (i = 0; i < 16; i = i + 1) begin
            a = i;
            #20;
        end 
        
        $finish;
    end
endmodule

EXP_NO_6/dec_4x16.vcd
$date
	Tue May 26 10:45:25 2026
$end
$version
	Icarus Verilog
$end
$timescale
	1ps
$end
$scope module tb_dec_4x16 $end
$var wire 16 ! b [15:0] $end
$var reg 4 " a [3:0] $end
$var integer 32 # i [31:0] $end
$scope module uut $end
$var wire 4 $ a [3:0] $end
$var reg 16 % b [15:0] $end
$upscope $end
$upscope $end
$enddefinitions $end
#0
$dumpvars
b1 %
b0 $
b0 #
b0 "
b1 !
$end
#20000
b10 !
b10 %
b1 "
b1 $
b1 #
#40000
b100 !
b100 %
b10 "
b10 $
b10 #
#60000
b1000 !
b1000 %
b11 "
b11 $
b11 #
#80000
b10000 !
b10000 %
b100 "
b100 $
b100 #
#100000
b100000 !
b100000 %
b101 "
b101 $
b101 #
#120000
b1000000 !
b1000000 %
b110 "
b110 $
b110 #
#140000
b10000000 !
b10000000 %
b111 "
b111 $
b111 #
#160000
b100000000 !
b100000000 %
b1000 "
b1000 $
b1000 #
#180000
b1000000000 !
b1000000000 %
b1001 "
b1001 $
b1001 #
#200000
b10000000000 !
b10000000000 %
b1010 "
b1010 $
b1010 #
#220000
b100000000000 !
b100000000000 %
b1011 "
b1011 $
b1011 #
#240000
b1000000000000 !
b1000000000000 %
b1100 "
b1100 $
b1100 #
#260000
b10000000000000 !
b10000000000000 %
b1101 "
b1101 $
b1101 #
#280000
b100000000000000 !
b100000000000000 %
b1110 "
b1110 $
b1110 #
#300000
b1000000000000000 !
b1000000000000000 %
b1111 "
b1111 $
b1111 #
#320000
b10000 #
