EXP_NO_19/down_counter_8bit.v
module down_counter_8bit(
input clk,
input rst,
output reg [7:0] count
);

always @(posedge clk)
begin

if(rst)
    count <= 8'd255;

else
    count <= count - 1'b1;

end

endmodule

EXP_NO_19/tb_down_counter_8bit.v
module tb_down_counter_8bit;

reg clk;
reg rst;

wire [7:0] count;

down_counter_8bit dut(
.clk(clk),
.rst(rst),
.count(count)
);

always #10 clk = ~clk;

initial begin

$dumpfile("down_counter.vcd");
$dumpvars(0,tb_down_counter_8bit);

clk = 0;
rst = 1;

#20;
rst = 0;

#500;

$finish;

end

initial begin
$monitor("time=%0t rst=%b count=%d",
          $time,rst,count);
end

endmodule

EXP_NO_19/down_counter.vcd
$date
	Tue Jun  2 18:05:53 2026
$end
$version
	Icarus Verilog
$end
$timescale
	1s
$end
$scope module tb_down_counter_8bit $end
$var wire 8 ! count [7:0] $end
$var reg 1 " clk $end
$var reg 1 # rst $end
$scope module dut $end
$var wire 1 " clk $end
$var wire 1 # rst $end
$var reg 8 $ count [7:0] $end
$upscope $end
$upscope $end
$enddefinitions $end
#0
$dumpvars
bx $
1#
0"
bx !
$end
#10
b11111111 !
b11111111 $
1"
#20
0"
0#
#30
b11111110 !
b11111110 $
1"
#40
0"
#50
b11111101 !
b11111101 $
1"
#60
0"
#70
b11111100 !
b11111100 $
1"
#80
0"
#90
b11111011 !
b11111011 $
1"
#100
0"
#110
b11111010 !
b11111010 $
1"
#120
0"
#130
b11111001 !
b11111001 $
1"
#140
0"
#150
b11111000 !
b11111000 $
1"
#160
0"
#170
b11110111 !
b11110111 $
1"
#180
0"
#190
b11110110 !
b11110110 $
1"
#200
0"
#210
b11110101 !
b11110101 $
1"
#220
0"
#230
b11110100 !
b11110100 $
1"
#240
0"
#250
b11110011 !
b11110011 $
1"
#260
0"
#270
b11110010 !
b11110010 $
1"
#280
0"
#290
b11110001 !
b11110001 $
1"
#300
0"
#310
b11110000 !
b11110000 $
1"
#320
0"
#330
b11101111 !
b11101111 $
1"
#340
0"
#350
b11101110 !
b11101110 $
1"
#360
0"
#370
b11101101 !
b11101101 $
1"
#380
0"
#390
b11101100 !
b11101100 $
1"
#400
0"
#410
b11101011 !
b11101011 $
1"
#420
0"
#430
b11101010 !
b11101010 $
1"
#440
0"
#450
b11101001 !
b11101001 $
1"
#460
0"
#470
b11101000 !
b11101000 $
1"
#480
0"
#490
b11100111 !
b11100111 $
1"
#500
0"
#510
b11100110 !
b11100110 $
1"
