EXP_NO_9/sr_dataflow.v
module sr_dataflow(
input s,
input r,
input clk,
output reg q
);

always @(posedge clk)
begin
q <= s | (~r & q);
end

endmodule

EXP_NO_9/tb_sr_dataflow.v
module tb_sr_dataflow;

reg s,r,clk;
wire q;

sr_dataflow dut(
.s(s),
.r(r),
.clk(clk),
.q(q)
);

always #5 clk = ~clk;

initial begin

$dumpfile("sr_dataflow.vcd");
$dumpvars(0,tb_sr_dataflow);

clk=0;

s=0;r=0; #10;
s=1;r=0; #10;
s=0;r=0; #10;
s=0;r=1; #10;
s=0;r=0; #10;
s=1;r=1; #10;

$finish;

end

initial
$monitor("time=%0t s=%b r=%b clk=%b q=%b",
          $time,s,r,clk,q);

endmodule

EXP_NO_9/sr_dataflow.vcd
$date
	Sun May 31 19:07:35 2026
$end
$version
	Icarus Verilog
$end
$timescale
	1s
$end
$scope module tb_sr_dataflow $end
$var wire 1 ! q $end
$var reg 1 " clk $end
$var reg 1 # r $end
$var reg 1 $ s $end
$scope module dut $end
$var wire 1 " clk $end
$var wire 1 # r $end
$var wire 1 $ s $end
$var reg 1 ! q $end
$upscope $end
$upscope $end
$enddefinitions $end
#0
$dumpvars
0$
0#
0"
x!
$end
#5
1"
#10
0"
1$
#15
1!
1"
#20
0"
0$
#25
1"
#30
0"
1#
#35
0!
1"
#40
0"
0#
#45
1"
#50
0"
1#
1$
#55
1!
1"
