EXP_NO_29/siso_8bit.v
module siso_8bit(
input clk,
input rst,
input serial_in,
output serial_out
);

reg [7:0] shift_reg;

always @(posedge clk)
begin

if(rst)
    shift_reg <= 8'b00000000;

else
    shift_reg <= {shift_reg[6:0], serial_in};

end

assign serial_out = shift_reg[7];

endmodule

EXP_NO_29/tb_siso_8bit.v
module tb_siso_8bit;

reg clk;
reg rst;
reg serial_in;

wire serial_out;

siso_8bit dut(
.clk(clk),
.rst(rst),
.serial_in(serial_in),
.serial_out(serial_out)
);

always #10 clk = ~clk;

initial begin

$dumpfile("siso.vcd");
$dumpvars(0,tb_siso_8bit);

clk = 0;
rst = 1;
serial_in = 0;

#20;
rst = 0;

// Send 10110011

serial_in = 1; #20;
serial_in = 0; #20;
serial_in = 1; #20;
serial_in = 1; #20;
serial_in = 0; #20;
serial_in = 0; #20;
serial_in = 1; #20;
serial_in = 1; #20;

// Extra clocks to observe output

serial_in = 0; #160;

$finish;

end

initial
begin

$monitor(
"time=%0t serial_in=%b serial_out=%b",
$time,
serial_in,
serial_out
);

end

endmodule

EXP_NO_29/siso.vcd
$date
	Wed Jun  3 19:08:10 2026
$end
$version
	Icarus Verilog
$end
$timescale
	1s
$end
$scope module tb_siso_8bit $end
$var wire 1 ! serial_out $end
$var reg 1 " clk $end
$var reg 1 # rst $end
$var reg 1 $ serial_in $end
$scope module dut $end
$var wire 1 " clk $end
$var wire 1 # rst $end
$var wire 1 $ serial_in $end
$var wire 1 ! serial_out $end
$var reg 8 % shift_reg [7:0] $end
$upscope $end
$upscope $end
$enddefinitions $end
#0
$dumpvars
bx %
0$
1#
0"
x!
$end
#10
0!
b0 %
1"
#20
0"
1$
0#
#30
b1 %
1"
#40
0"
0$
#50
b10 %
1"
#60
0"
1$
#70
b101 %
1"
#80
0"
#90
b1011 %
1"
#100
0"
0$
#110
b10110 %
1"
#120
0"
#130
b101100 %
1"
#140
0"
1$
#150
b1011001 %
1"
#160
0"
#170
1!
b10110011 %
1"
#180
0"
0$
#190
0!
b1100110 %
1"
#200
0"
#210
1!
b11001100 %
1"
#220
0"
#230
b10011000 %
1"
#240
0"
#250
0!
b110000 %
1"
#260
0"
#270
b1100000 %
1"
#280
0"
#290
1!
b11000000 %
1"
#300
0"
#310
b10000000 %
1"
#320
0"
#330
0!
b0 %
1"
