EXP_NO_12/exp_12.v
module exp_12(
input clk , d,q_ff,
output reg q_latch );

always @(posedge clk) begin 
if (d == 1 && q_ff == 1 )
q_latch <= 1 ;
else 
q_latch <= 0 ;
end 
endmodule

EXP_NO_12/tb_exp_12.v
module tb_exp_12;
wire q_latch;
reg clk , d, q_ff;

exp_12 e1 (
.q_latch(q_latch),.clk(clk),.d(d),.q_ff(q_ff));

always #5 clk = ~clk;

initial begin 
$dumpfile ("exp12.vcd");
$dumpvars (0,tb_exp_12);

d   = 0;
clk = 0;
#20  d = 1;     
#10; q_ff= 1 ;

#10  d = 0;      
#10; q_ff= 0 ;

#10  d = 1;
#10  d = 0;


#10  d = 1;
#10  d = 0;
#20; q_ff= 1 ;

#10  d = 0;



#10  d = 1;
#10  d = 0;



#20;
$finish;

end 
endmodule

EXP_NO_12/exp12.vcd
$date
	Mon Jun  1 07:12:43 2026
$end
$version
	Icarus Verilog
$end
$timescale
	1s
$end
$scope module tb_exp_12 $end
$var wire 1 ! q_latch $end
$var reg 1 " clk $end
$var reg 1 # d $end
$var reg 1 $ q_ff $end
$scope module e1 $end
$var wire 1 " clk $end
$var wire 1 # d $end
$var wire 1 $ q_ff $end
$var reg 1 ! q_latch $end
$upscope $end
$upscope $end
$enddefinitions $end
#0
$dumpvars
x$
0#
0"
x!
$end
#5
0!
1"
#10
0"
#15
1"
#20
0"
1#
#25
1"
#30
0"
1$
#35
1!
1"
#40
0"
0#
#45
0!
1"
#50
0"
0$
#55
1"
#60
0"
1#
#65
1"
#70
0"
0#
#75
1"
#80
0"
1#
#85
1"
#90
0"
0#
#95
1"
#100
0"
#105
1"
#110
0"
1$
#115
1"
#120
0"
#125
1"
#130
0"
1#
#135
1!
1"
#140
0"
0#
#145
0!
1"
