EXP_NO_2/fulladder/or1.v
module or1 (
input a , b ,
output out1);
assign out1 = a | b ;
endmodule

EXP_NO_2/fulladder/halfadder_ST.v
module halfadder_ST(
input a , b , 
output sum , carry );

assign sum =  a ^ b ;
assign carry = a & b ;
endmodule

EXP_NO_2/fulladder/fulladder_ST.v
module fulladder_ST(
input a , b , cin ,
output sum , carry );

wire sum1 ;
wire carry1 ;
wire carry2 ;
halfadder_ST h1 (.a(a),.b(b),.sum(sum1),.carry(carry1));
halfadder_ST h2 (.a(sum1),.b(cin),.sum(sum),.carry(carry2));
or1 o1 (.a(carry1),.b(carry2),.out1(carry));
endmodule

EXP_NO_2/fulladder/fulladder_tb.v
module fulladder_tb;
reg a , b , cin ;
output sum , carry ;

fulladder_ST d1 (.a(a),.b(b),.cin(cin),.sum(sum),.carry(carry));

initial begin 
$dumpfile ("fulladder.vcd");
$dumpvars(0,fulladder_tb);
repeat (20) begin 
a = $random %2;
b = $random %2;
cin = $random %2;
$display (" time = %t , a = %d , b = %d , cin = %d ,sum = %d , carry = %d ",$time , a, b ,cin, sum , carry );
#20;
end
end 
endmodule

EXP_NO_2/fulladder/fulladder.vcd
$date
	Sat May 16 15:13:24 2026
$end
$version
	Icarus Verilog
$end
$timescale
	1s
$end
$scope module fulladder_tb $end
$var wire 1 ! sum $end
$var wire 1 " carry $end
$var reg 1 # a $end
$var reg 1 $ b $end
$var reg 1 % cin $end
$scope module d1 $end
$var wire 1 # a $end
$var wire 1 $ b $end
$var wire 1 % cin $end
$var wire 1 & sum1 $end
$var wire 1 ! sum $end
$var wire 1 ' carry2 $end
$var wire 1 ( carry1 $end
$var wire 1 " carry $end
$scope module h1 $end
$var wire 1 # a $end
$var wire 1 $ b $end
$var wire 1 ( carry $end
$var wire 1 & sum $end
$upscope $end
$scope module h2 $end
$var wire 1 & a $end
$var wire 1 % b $end
$var wire 1 ' carry $end
$var wire 1 ! sum $end
$upscope $end
$scope module o1 $end
$var wire 1 ( a $end
$var wire 1 ' b $end
$var wire 1 " out1 $end
$upscope $end
$upscope $end
$upscope $end
$enddefinitions $end
#0
$dumpvars
0(
1'
1&
1%
1$
0#
1"
0!
$end
#20
1!
0'
0&
1(
1#
#40
0!
1'
1"
1&
0(
0$
#100
0"
1!
0'
0%
1$
0#
#120
0!
1"
0&
1(
1#
#140
1!
0"
1&
0(
0$
#160
1$
0#
#180
1"
0&
1(
1%
1#
#200
0"
1&
0(
0%
0$
#220
0&
1%
0#
#240
1"
0!
1'
1&
1$
#260
1!
0'
0&
1(
1#
#280
0"
0(
0$
0#
#300
1"
0!
1(
0%
1$
1#
#320
0"
0(
0$
0#
#340
1!
1&
1$
#360
1"
0!
1'
1%
#380
0"
0'
0&
0%
0$
