EXP_NO_5/bm_prio.v
module bm_prio (
input [3:0] y ,
output reg [1:0] a ,
output reg v );



always @(*) begin 

if (y[3] == 1 ) begin
a  = 2'b11;
v = 1 ;
end

else if (y[2] == 1 ) begin
a  = 2'b10;
v = 1 ;
end

else if (y[3] == 1 ) begin
a  = 2'b01;
v = 1 ;
end

else if (y[3] == 1 ) begin
a  = 2'b00;
v = 1 ;
end

else begin 
v = 0 ;
a = 2'b00;

end 
end
endmodule

EXP_NO_5/bm_tb_prio.v
module bm_tb_prio;
reg [3:0] y ;
wire [1:0] a ; 
wire v ;


bm_prio p1 (
.y(y),.a(a),.v(v));

initial begin 

$dumpfile ("bm_prio.vcd");
$dumpvars (0,bm_tb_prio);

repeat (20) begin 
y = $random %16 ;
#20 ;
$display ("y = %b , a = %b , v = %b ", y , a ,  v );
end 

end 
endmodule

EXP_NO_5/bm_prio.vcd
$date
	Tue May 26 09:53:48 2026
$end
$version
	Icarus Verilog
$end
$timescale
	1s
$end
$scope module bm_tb_prio $end
$var wire 1 ! v $end
$var wire 2 " a [1:0] $end
$var reg 4 # y [3:0] $end
$scope module p1 $end
$var wire 4 $ y [3:0] $end
$var reg 2 % a [1:0] $end
$var reg 1 ! v $end
$upscope $end
$upscope $end
$enddefinitions $end
#0
$dumpvars
b10 %
b100 $
b100 #
b10 "
1!
$end
#20
b0 "
b0 %
0!
b1 #
b1 $
#40
1!
b11 "
b11 %
b1001 #
b1001 $
#60
b0 "
b0 %
0!
b11 #
b11 $
#80
1!
b11 "
b11 %
b1101 #
b1101 $
#120
b10 "
b10 %
b101 #
b101 $
#140
b0 "
b0 %
0!
b10 #
b10 $
#160
b1 #
b1 $
#180
1!
b11 "
b11 %
b1101 #
b1101 $
#200
b10 "
b10 %
b110 #
b110 $
#220
b11 "
b11 %
b1101 #
b1101 $
#260
b1100 #
b1100 $
#280
b1001 #
b1001 $
#300
b10 "
b10 %
b110 #
b110 $
#320
b101 #
b101 $
#340
b11 "
b11 %
b1010 #
b1010 $
#360
b10 "
b10 %
b101 #
b101 $
#380
b111 #
b111 $
