EXP_NO_5/df_prio.v
module df_prio (
input [3:0] y ,
output [1:0] a ,
output v );


assign a[1] = y[3] | (~y[2] & y[1] );
assign a[0] = y[3] | y[2] ;
assign v = y[3] | y[2] | y[1] | y[0] ;

endmodule

EXP_NO_5/df_tb_prio.v
module df_tb_prio;
reg [3:0] y ;
wire [1:0] a ; 
wire v ;


df_prio p1 (
.y(y),.a(a),.v(v));

initial begin 

$dumpfile ("df_prio.vcd");
$dumpvars (0,df_tb_prio);

repeat (20) begin 
y = $random %16 ;
#20 ;
$display ("y = %b , a = %b , v = %b ", y , a ,  v );
end 

end 
endmodule

EXP_NO_5/df_prio.vcd
$date
	Tue May 26 09:44:36 2026
$end
$version
	Icarus Verilog
$end
$timescale
	1s
$end
$scope module df_tb_prio $end
$var wire 1 ! v $end
$var wire 2 " a [1:0] $end
$var reg 4 # y [3:0] $end
$scope module p1 $end
$var wire 1 ! v $end
$var wire 4 $ y [3:0] $end
$var wire 2 % a [1:0] $end
$upscope $end
$upscope $end
$enddefinitions $end
#0
$dumpvars
b1 %
b100 $
b100 #
b1 "
1!
$end
#20
b0 "
b0 %
b1 #
b1 $
#40
b11 "
b11 %
b1001 #
b1001 $
#60
b10 "
b10 %
b11 #
b11 $
#80
b11 "
b11 %
b1101 #
b1101 $
#120
b1 "
b1 %
b101 #
b101 $
#140
b10 "
b10 %
b10 #
b10 $
#160
b0 "
b0 %
b1 #
b1 $
#180
b11 "
b11 %
b1101 #
b1101 $
#200
b1 "
b1 %
b110 #
b110 $
#220
b11 "
b11 %
b1101 #
b1101 $
#260
b1100 #
b1100 $
#280
b1001 #
b1001 $
#300
b1 "
b1 %
b110 #
b110 $
#320
b101 #
b101 $
#340
b11 "
b11 %
b1010 #
b1010 $
#360
b1 "
b1 %
b101 #
b101 $
#380
b111 #
b111 $
