EXP_NO_5/sm_prio.v
module sm_prio(
input [3:0] y ,
output [1:0] a ,
output v );


wire not_y2;
    wire and_out;

    not gate_not (not_y2, y[2]);


    and gate_and (and_out, not_y2, y[1]);


    or gate_a1 (a[1], y[3], and_out);


    or gate_a0 (a[0], y[3], y[2]);


    or gate_v (v, y[3], y[2], y[1], y[0]);
    
    endmodule

EXP_NO_5/sm_tb__prio.v
module sm_tb__prio;
reg [3:0] y ;
wire [1:0] a ; 
wire v ;


sm_prio p1 (
.y(y),.a(a),.v(v));

initial begin 

$dumpfile ("sm_prio.vcd");
$dumpvars (0,sm_tb__prio);

repeat (20) begin 
y = $random %16 ;
#20 ;
$display ("y = %b , a = %b , v = %b ", y , a ,  v );
end 

end 
endmodule

EXP_NO_5/sm_prio.vcd
$date
	Tue May 26 10:01:37 2026
$end
$version
	Icarus Verilog
$end
$timescale
	1s
$end
$scope module sm_tb__prio $end
$var wire 1 ! v $end
$var wire 2 " a [1:0] $end
$var reg 4 # y [3:0] $end
$scope module p1 $end
$var wire 1 $ and_out $end
$var wire 1 % not_y2 $end
$var wire 1 ! v $end
$var wire 4 & y [3:0] $end
$var wire 2 ' a [1:0] $end
$upscope $end
$upscope $end
$enddefinitions $end
#0
$dumpvars
b1 '
b100 &
0%
0$
b100 #
b1 "
1!
$end
#20
1%
b0 "
b0 '
b1 #
b1 &
#40
b11 "
b11 '
b1001 #
b1001 &
#60
1$
b10 "
b10 '
b11 #
b11 &
#80
0%
0$
b11 "
b11 '
b1101 #
b1101 &
#120
b1 "
b1 '
b101 #
b101 &
#140
1$
1%
b10 "
b10 '
b10 #
b10 &
#160
b0 "
b0 '
0$
b1 #
b1 &
#180
0%
b11 "
b11 '
b1101 #
b1101 &
#200
b1 "
b1 '
b110 #
b110 &
#220
b11 "
b11 '
b1101 #
b1101 &
#260
b1100 #
b1100 &
#280
1%
b1001 #
b1001 &
#300
0%
0$
b1 "
b1 '
b110 #
b110 &
#320
b101 #
b101 &
#340
1$
1%
b11 "
b11 '
b1010 #
b1010 &
#360
b1 "
b1 '
0%
0$
b101 #
b101 &
#380
b111 #
b111 &
