EXP_NO_3/EXP_NO_3_B_FINAL/encoder_8to3_sm.v
module encoder_8to3_sm (
    input wire [7:0] Y,
    output wire [2:0] A
);

    or gate2 (A[2], Y[7], Y[6], Y[5], Y[4]);
    or gate1 (A[1], Y[7], Y[6], Y[3], Y[2]);
    or gate0 (A[0], Y[7], Y[5], Y[3], Y[1]);
endmodule

EXP_NO_3/EXP_NO_3_B_FINAL/tb_encoder_8to3_sm.v

module tb_encoder_8to3_sm;
    reg [7:0] Y;
    wire [2:0] A;

    encoder_8to3_sm uut (
        .Y(Y),
        .A(A)
    );

    integer i;
    initial begin
        $monitor("Time=%0t | Input Y=%b | Output A=%b", $time, Y, A);
        $dumpfile ("sm8encoder.vcd");
        $dumpvars (0,tb_encoder_8to3_sm);
        for (i = 0; i < 8; i = i + 1) begin
            Y = (1 << i);
            #10;
        end
        
        $finish;
    end
endmodule

EXP_NO_3/EXP_NO_3_B_FINAL/sm8encoder.vcd
$date
	Wed May 20 10:56:51 2026
$end
$version
	Icarus Verilog
$end
$timescale
	1s
$end
$scope module tb_encoder_8to3_sm $end
$var wire 3 ! A [2:0] $end
$var reg 8 " Y [7:0] $end
$var integer 32 # i [31:0] $end
$scope module uut $end
$var wire 8 $ Y [7:0] $end
$var wire 3 % A [2:0] $end
$upscope $end
$upscope $end
$enddefinitions $end
#0
$dumpvars
b0 %
b1 $
b0 #
b1 "
b0 !
$end
#10
b1 !
b1 %
b10 "
b10 $
b1 #
#20
b10 !
b10 %
b100 "
b100 $
b10 #
#30
b11 !
b11 %
b1000 "
b1000 $
b11 #
#40
b100 !
b100 %
b10000 "
b10000 $
b100 #
#50
b101 !
b101 %
b100000 "
b100000 $
b101 #
#60
b110 !
b110 %
b1000000 "
b1000000 $
b110 #
#70
b111 !
b111 %
b10000000 "
b10000000 $
b111 #
#80
b1000 #
