EXP_NO_14/jk.v
module jk(
input clk , j , k ,
output reg q);

always @(posedge clk)begin

q <= ((j & (~q)) | (~k & q ));
end 
endmodule

EXP_NO_13/ms_jk.v
module ms_jk(
input clk,
input j,
input k,
output q
);

wire qm;
wire clk_bar;

not n1(clk_bar,clk);

jk master(
.clk(clk),
.j(j),
.k(k),
.q(qm)
);

jk slave(
.clk(clk_bar),
.j(qm),
.k(~qm),
.q(q)
);

endmodule

EXP_NO_13/tb_ms_jk.v
module tb_ms_jk;

reg clk,j,k;
wire q;

ms_jk dut(
.clk(clk),
.j(j),
.k(k),
.q(q)
);

always #10 clk = ~clk;

initial begin

$dumpfile("ms_jk.vcd");
$dumpvars(0,tb_ms_jk);

clk = 0;


j=0; k=0; #20;


j=0; k=1; #20;


j=1; k=0; #20;


j=1; k=1; #20;


j=0; k=0; #20;


j=1; k=1; #20;

$finish;

end

initial
$monitor("t=%0t clk=%b j=%b k=%b q=%b",
          $time,clk,j,k,q);

endmodule

EXP_NO_13/ms_jk.vcd
$date
	Mon Jun  1 07:40:04 2026
$end
$version
	Icarus Verilog
$end
$timescale
	1s
$end
$scope module tb_ms_jk $end
$var wire 1 ! q $end
$var reg 1 " clk $end
$var reg 1 # j $end
$var reg 1 $ k $end
$scope module dut $end
$var wire 1 " clk $end
$var wire 1 % clk_bar $end
$var wire 1 # j $end
$var wire 1 $ k $end
$var wire 1 & qm $end
$var wire 1 ! q $end
$scope module master $end
$var wire 1 " clk $end
$var wire 1 # j $end
$var wire 1 $ k $end
$var reg 1 & q $end
$upscope $end
$scope module slave $end
$var wire 1 % clk $end
$var wire 1 & j $end
$var wire 1 ' k $end
$var reg 1 ! q $end
$upscope $end
$upscope $end
$upscope $end
$enddefinitions $end
#0
$dumpvars
x'
x&
1%
0$
0#
0"
x!
$end
#10
0%
1"
#20
1%
0"
1$
#30
1'
0&
0%
1"
#40
0!
1%
0"
0$
1#
#50
0'
1&
0%
1"
#60
1!
1%
0"
1$
#70
1'
0&
0%
1"
#80
0!
1%
0"
0$
0#
#90
0%
1"
#100
1%
0"
1$
1#
#110
0'
1&
0%
1"
#120
1!
1%
0"
