EXP_NO_15/async_dff.v
module async_dff(
input clk,
input d,
input pre,
input clr,
output reg q
);

always @(posedge clk or posedge pre or posedge clr)
begin

if(clr)
    q <= 0;

else if(pre)
    q <= 1;

else
    q <= d;

end

endmodule

EXP_NO_15/tb_async_dff.v
module tb_async_dff;

reg clk;
reg d;
reg pre;
reg clr;

wire q;

async_dff dut(
.clk(clk),
.d(d),
.pre(pre),
.clr(clr),
.q(q)
);

always #10 clk = ~clk;

initial begin

$dumpfile("async_dff.vcd");
$dumpvars(0,tb_async_dff);

clk = 0;
d   = 0;
pre = 0;
clr = 0;

// Normal DFF Operation
#15 d = 1;
#20 d = 0;

// Asynchronous Preset
#5  pre = 1;
#10 pre = 0;

// Normal Operation
#15 d = 1;

// Asynchronous Clear
#5  clr = 1;
#10 clr = 0;

// Normal Operation
#20 d = 0;
#20 d = 1;

#20;
$finish;

end

initial begin
$monitor("time=%0t clk=%b d=%b pre=%b clr=%b q=%b",
          $time,clk,d,pre,clr,q);
end

endmodule

EXP_NO_15/async_dff.vcd
$date
	Tue Jun  2 17:11:10 2026
$end
$version
	Icarus Verilog
$end
$timescale
	1s
$end
$scope module tb_async_dff $end
$var wire 1 ! q $end
$var reg 1 " clk $end
$var reg 1 # clr $end
$var reg 1 $ d $end
$var reg 1 % pre $end
$scope module dut $end
$var wire 1 " clk $end
$var wire 1 # clr $end
$var wire 1 $ d $end
$var wire 1 % pre $end
$var reg 1 ! q $end
$upscope $end
$upscope $end
$enddefinitions $end
#0
$dumpvars
0%
0$
0#
0"
x!
$end
#10
0!
1"
#15
1$
#20
0"
#30
1!
1"
#35
0$
#40
1%
0"
#50
0!
0%
1"
#60
0"
#65
1$
#70
1#
1"
#80
0#
0"
#90
1!
1"
#100
0"
0$
#110
0!
1"
#120
0"
1$
#130
1!
1"
