EXP_NO_17/tff_sync_async.v
module tff_sync_async(
input clk,
input t,
input arst,
input srst,
output reg q,
output qbar
);

always @(posedge clk or posedge arst)
begin

if(arst)
    q <= 1'b0;

else if(srst)
    q <= 1'b0;

else if(t)
    q <= ~q;

else
    q <= q;

end

assign qbar = ~q;

endmodule

EXP_NO_17/tb_tff_sync_async.v
module tb_tff_sync_async;

reg clk;
reg t;
reg arst;
reg srst;

wire q;
wire qbar;

tff_sync_async dut(
.clk(clk),
.t(t),
.arst(arst),
.srst(srst),
.q(q),
.qbar(qbar)
);

always #10 clk = ~clk;

initial begin

$dumpfile("tff_sync_async.vcd");
$dumpvars(0,tb_tff_sync_async);

clk  = 0;
t    = 0;
arst = 0;
srst = 0;

// Toggle
#15;
t = 1;

#20;

// Toggle again
#20;

// Asynchronous Reset
arst = 1;

#5;

arst = 0;

// Toggle
#20;
t = 1;

#20;

// Synchronous Reset
srst = 1;

#5;

// Wait for next posedge clk
#20;

srst = 0;

// Toggle again
#20;
t = 1;

#40;

$finish;

end

initial begin

$monitor(
"time=%0t clk=%b t=%b arst=%b srst=%b q=%b qbar=%b",
$time,clk,t,arst,srst,q,qbar
);

end

endmodule

EXP_NO_17/tff_sync_async.vcd
$date
	Tue Jun  2 17:45:57 2026
$end
$version
	Icarus Verilog
$end
$timescale
	1s
$end
$scope module tb_tff_sync_async $end
$var wire 1 ! qbar $end
$var wire 1 " q $end
$var reg 1 # arst $end
$var reg 1 $ clk $end
$var reg 1 % srst $end
$var reg 1 & t $end
$scope module dut $end
$var wire 1 # arst $end
$var wire 1 $ clk $end
$var wire 1 ! qbar $end
$var wire 1 % srst $end
$var wire 1 & t $end
$var reg 1 " q $end
$upscope $end
$upscope $end
$enddefinitions $end
#0
$dumpvars
0&
0%
0$
0#
x"
x!
$end
#10
1$
#15
1&
#20
0$
#30
1$
#40
0$
#50
1$
#55
1!
0"
1#
#60
0#
0$
#70
0!
1"
1$
#80
0$
#90
1!
0"
1$
#100
0$
1%
#110
1$
#120
0$
#125
0%
#130
0!
1"
1$
#140
0$
#150
1!
0"
1$
#160
0$
#170
0!
1"
1$
