EXP_NO_32/seq_detector_1111.v
module seq_detector_1111(
input clk,
input rst,
input x,
output reg z
);

reg [2:0] state;

parameter S0 = 3'b000;
parameter S1 = 3'b001;
parameter S2 = 3'b010;
parameter S3 = 3'b011;
parameter S4 = 3'b100;

always @(posedge clk)
begin

if(rst)
begin
    state <= S0;
    z <= 0;
end

else
begin

case(state)

S0:
begin
    z <= 0;
    if(x)
        state <= S1;
    else
        state <= S0;
end

S1:
begin
    z <= 0;
    if(x)
        state <= S2;
    else
        state <= S0;
end

S2:
begin
    z <= 0;
    if(x)
        state <= S3;
    else
        state <= S0;
end

S3:
begin
    if(x)
    begin
        state <= S0;
        z <= 1;
    end
    else
    begin
        state <= S0;
        z <= 0;
    end
end

default:
begin
    state <= S0;
    z <= 0;
end

endcase

end

end

endmodule

EXP_NO_32/tb_seq_detector_1111.v
module tb_seq_detector_1111;

reg clk;
reg rst;
reg x;

wire z;

seq_detector_1111 dut(
.clk(clk),
.rst(rst),
.x(x),
.z(z)
);

always #10 clk = ~clk;

initial begin

$dumpfile("seq1111.vcd");
$dumpvars(0,tb_seq_detector_1111);

clk = 0;
rst = 1;
x   = 0;

#20;
rst = 0;

// 001110
x=0; #20;
x=0; #20;
x=1; #20;
x=1; #20;
x=1; #20;
x=0; #20;

// 1111 detected
x=1; #20;
x=1; #20;
x=1; #20;
x=1; #20;

// 0011
x=0; #20;
x=0; #20;
x=1; #20;
x=1; #20;

// another 1111
x=1; #20;
x=1; #20;
x=1; #20;
x=1; #20;

#40;

$finish;

end

initial
$monitor(
"time=%0t x=%b z=%b",
$time,x,z
);

endmodule

EXP_NO_32/seq1111.vcd
$date
	Wed Jun  3 19:23:11 2026
$end
$version
	Icarus Verilog
$end
$timescale
	1s
$end
$scope module tb_seq_detector_1111 $end
$var wire 1 ! z $end
$var reg 1 " clk $end
$var reg 1 # rst $end
$var reg 1 $ x $end
$scope module dut $end
$var wire 1 " clk $end
$var wire 1 # rst $end
$var wire 1 $ x $end
$var reg 3 % state [2:0] $end
$var reg 1 ! z $end
$upscope $end
$upscope $end
$enddefinitions $end
#0
$dumpvars
bx %
0$
1#
0"
x!
$end
#10
0!
b0 %
1"
#20
0"
0#
#30
1"
#40
0"
#50
1"
#60
0"
1$
#70
b1 %
1"
#80
0"
#90
b10 %
1"
#100
0"
#110
b11 %
1"
#120
0"
0$
#130
b0 %
1"
#140
0"
1$
#150
b1 %
1"
#160
0"
#170
b10 %
1"
#180
0"
#190
b11 %
1"
#200
0"
#210
1!
b0 %
1"
#220
0"
0$
#230
0!
1"
#240
0"
#250
1"
#260
0"
1$
#270
b1 %
1"
#280
0"
#290
b10 %
1"
#300
0"
#310
b11 %
1"
#320
0"
#330
1!
b0 %
1"
#340
0"
#350
b1 %
0!
1"
#360
0"
#370
b10 %
1"
#380
0"
#390
b11 %
1"
#400
0"
#410
1!
b0 %
1"
