EXP_NO_3/half_sub/half_sub.v
//dataflow 
module half_sub (
input a , b ,
output borrow , difference );

assign borrow =~a & b ;
assign difference =  a ^ b ;
endmodule

EXP_NO_3/half_sub/half_sub_tb.v
module half_sub_tb ;
reg a , b ;
wire borrow , differnce ;

half_sub s1 (.a(a),.b(b),.borrow(borrow),.difference(difference));

initial begin 
$dumpfile ("half_sub_SM.vcd");
$dumpvars(0,half_sub_tb);
repeat (20) begin 
a = $random %2 ;
b = $random %2;
#20;
$display ("a = %d , b = %d , borrow = %d , difference = %d " , a,b,borrow,difference);
end 
$finish;
end 
endmodule

EXP_NO_3/half_sub/half_sub_SM.vcd
$date
	Sun May 17 10:13:41 2026
$end
$version
	Icarus Verilog
$end
$timescale
	1s
$end
$scope module half_sub_tb $end
$var wire 1 ! difference $end
$var wire 1 " borrow $end
$var reg 1 # a $end
$var reg 1 $ b $end
$scope module s1 $end
$var wire 1 # a $end
$var wire 1 $ b $end
$var wire 1 " borrow $end
$var wire 1 ! difference $end
$upscope $end
$upscope $end
$enddefinitions $end
#0
$dumpvars
1$
0#
1"
1!
$end
#20
0"
0!
1#
#60
1!
0$
#80
0!
1$
#100
1"
1!
0#
#120
0"
0$
1#
#180
0!
1$
#200
1"
1!
0#
#220
0"
0!
0$
#240
1"
1!
1$
#280
0"
0!
1#
#300
1!
0$
#320
0!
0#
#340
1"
1!
1$
#380
0"
0!
1#
